{
  "courses": [
    {
      "name": "Pure Redux",
      "price": "12",
      "id": 1
    },
    {
      "name": "Pure React",
      "price": "32",
      "id": 2
    }
  ],
  "lessons": [
    {
      "title": "Nuova lezione modificata",
      "courseId": 1,
      "id": 1
    },
    {
      "title": "Imparare i verbi yes!",
      "courseId": 1,
      "id": 2
    },
    {
      "title": "Imparare RTK",
      "courseId": 1,
      "id": 3
    },
    {
      "title": "Imparare testinh",
      "courseId": 1,
      "id": 4
    },
    {
      "title": "react fondamenti",
      "courseId": 2,
      "id": 5
    },
    {
      "title": "react avanzato",
      "courseId": 2,
      "id": 6
    },
    {
      "title": "Hooks",
      "courseId": 2,
      "id": 7
    }
  ]
}